Workbook
Name valuevx: 42.314159

Sheet HRRampUp
C2: ="Year "&1 -> Year 1 | G2: ="Year "&2 -> Year 2 | K2: ="Year "&3 -> Year 3 | O2: ="Year "&4 -> Year 4 | S2: ="Year "&5 -> Year 5
C3: Q1 | D3: Q2 | E3: Q3 | F3: Q4 | G3: Q1 | H3: Q2 | I3: Q3 | J3: Q4 | K3: Q1 | L3: Q2 | M3: Q3 | N3: Q4 | O3: Q1 | P3: Q2 | Q3: Q3 | R3: Q4 | S3: Q1 | T3: Q2 | U3: Q3 | V3: Q4
B4: CTO | C4: 1 | D4: 1 | E4: 1 | F4: 1 | G4: 1 | H4: 1 | I4: 1 | J4: 1 | K4: 1 | L4: 1 | M4: 1 | N4: 1 | O4: 1 | P4: 1 | Q4: 1 | R4: 1 | S4: 1 | T4: 1 | U4: 1 | V4: 1
B5: Full-Stack Developer | K5: 1 | L5: 1 | M5: 1 | N5: 1 | O5: 1 | P5: 1 | Q5: 1 | R5: 1 | S5: 1 | T5: 1 | U5: 1 | V5: 1
B6: UI/UX Designer | C6: 1 | D6: 1 | E6: 1 | F6: 1 | G6: 1 | H6: 1 | I6: 1 | J6: 1 | K6: 1 | L6: 1 | M6: 1 | N6: 1 | O6: 1 | P6: 1 | Q6: 1 | R6: 1 | S6: 1 | T6: 1 | U6: 1 | V6: 1
B7: Solution Architect | C7: 1 | D7: 1 | E7: 1 | F7: 1 | G7: 1 | H7: 1 | I7: 1 | J7: 1 | K7: 1 | L7: 1 | M7: 1 | N7: 1 | O7: 1 | P7: 1 | Q7: 1 | R7: 1 | S7: 1 | T7: 1 | U7: 1 | V7: 1
B8: Backend Engineer | O8: 1 | P8: 1 | Q8: 1 | R8: 1 | S8: 1 | T8: 1 | U8: 1 | V8: 1
B9: Data/AI Engineer | C9: 1 | D9: 1 | E9: 1 | F9: 1 | G9: 1 | H9: 1 | I9: 1 | J9: 1 | K9: 1 | L9: 1 | M9: 1 | N9: 1 | O9: 1 | P9: 1 | Q9: 1 | R9: 1 | S9: 1 | T9: 1 | U9: 1 | V9: 1
B10: Marketing Manager | O10: 1 | P10: 1 | Q10: 1 | R10: 1 | S10: 1 | T10: 1 | U10: 1 | V10: 1
B11: Digital Marketing Specialist | D11: 1 | E11: 1 | F11: 1 | G11: 1 | H11: 1 | I11: 1 | J11: 1 | K11: 1 | L11: 1 | M11: 1 | N11: 1 | O11: 1 | P11: 2 | Q11: 2 | R11: 2 | S11: 2 | T11: 2 | U11: 2 | V11: 2
B12: Campus Partnerships Specialist | H12: 1 | I12: 1 | J12: 1 | K12: 1 | L12: 1 | M12: 1 | N12: 1 | O12: 1 | P12: 2 | Q12: 2 | R12: 2 | S12: 2 | T12: 2 | U12: 2 | V12: 2
B13: Quality Assurance (QA) Engineer | K13: 1 | L13: 1 | M13: 1 | N13: 1 | O13: 1 | P13: 1 | Q13: 1 | R13: 1 | S13: 1 | T13: 1 | U13: 1 | V13: 1
B14: Customer Support Lead | O14: 1 | P14: 1 | Q14: 1 | R14: 1 | S14: 1 | T14: 1 | U14: 1 | V14: 1
B15: Human Resources (HR) Manager | N15: 1 | O15: 1 | P15: 1 | Q15: 1 | R15: 1 | S15: 1 | T15: 1 | U15: 1 | V15: 1
B16: Product Manager | O16: 1 | P16: 1 | Q16: 1 | R16: 1 | S16: 1 | T16: 1 | U16: 1 | V16: 1
B17: DevOps Engineer | O17: 1 | P17: 1 | Q17: 1 | R17: 1 | S17: 1 | T17: 1 | U17: 1 | V17: 1
B18: Customer Support Representative | K18: 1 | L18: 1 | M18: 1 | N18: 1 | O18: 1 | P18: 1 | Q18: 1 | R18: 1 | S18: 1 | T18: 1 | U18: 1 | V18: 1
B19: Account Manager | O19: 1 | P19: 1 | Q19: 1 | R19: 1 | S19: 1 | T19: 1 | U19: 1 | V19: 1
B20: Legal Counsel
B21: Bookkeeper | S21: 1 | T21: 1 | U21: 1 | V21: 1
B22: Accountant
B23: TOTAL HC | C23: =SUM(C4:C22) -> 4 | D23: =SUM(D4:D22) -> 5 | E23: =SUM(E4:E22) -> 5 | F23: =SUM(F4:F22) -> 5 | G23: =SUM(G4:G22) -> 5 | H23: =SUM(H4:H22) -> 6 | I23: =SUM(I4:I22) -> 6 | J23: =SUM(J4:J22) -> 6 | ... V23: =SUM(V4:V22) -> 19

Sheet CostExpense
C2: =HRRampUp!C2 -> Year 1 | G2: =HRRampUp!G2 -> Year 2 | K2: =HRRampUp!K2 -> Year 3 | O2: =HRRampUp!O2 -> Year 4 | S2: =HRRampUp!S2 -> Year 5
C3: =HRRampUp!C3 -> Q1 | D3: =HRRampUp!D3 -> Q2 | E3: =HRRampUp!E3 -> Q3 | F3: =HRRampUp!F3 -> Q4 | G3: =HRRampUp!G3 -> Q1 | H3: =HRRampUp!H3 -> Q2 | I3: =HRRampUp!I3 -> Q3 | J3: =HRRampUp!J3 -> Q4 | ... V3: =HRRampUp!V3 -> Q4
B4: Accounting and Legal | C4: 2000 | D4: 1000 | E4: 1000 | F4: 1000 | G4: 1000 | H4: 1000 | I4: 1000 | J4: 1000 | K4: 1000 | L4: 1000 | M4: 1000 | N4: 1000 | O4: 1000 | P4: 1000 | Q4: 1000 | R4: 2000 | S4: 2000 | T4: 2000 | U4: 2000 | V4: 2000
B5: Dues and Subscriptions | C5: =500*3 -> 1500 | D5: =500*3 -> 1500 | E5: =500*3 -> 1500 | F5: =500*3 -> 1500 | G5: =500*3 -> 1500 | H5: =500*3 -> 1500 | I5: =500*3 -> 1500 | J5: =500*3 -> 1500 | ... V5: =500*3 -> 1500
B6: Depreciation, Insurance | C6: =200*3 -> 600 | D6: =200*3 -> 600 | E6: =200*3 -> 600 | F6: =200*3 -> 600 | G6: =200*3 -> 600 | H6: =200*3 -> 600 | I6: =200*3 -> 600 | J6: =200*3 -> 600 | ... V6: =200*3 -> 600
B7: Maintenance and Repairs | C7: =200*3 -> 600 | D7: =200*3 -> 600 | E7: =200*3 -> 600 | F7: =200*3 -> 600 | G7: =200*3 -> 600 | H7: =200*3 -> 600 | I7: =200*3 -> 600 | J7: =200*3 -> 600 | ... V7: =200*3 -> 600
B8: Office Supplies | C8: =200*3 -> 600 | D8: =200*3 -> 600 | E8: =200*3 -> 600 | F8: =200*3 -> 600 | G8: =200*3 -> 600 | H8: =200*3 -> 600 | I8: =200*3 -> 600 | J8: =200*3 -> 600 | ... N8: =200*3 -> 600 | O8: =400*3 -> 1200 | P8: =400*3 -> 1200 | Q8: =400*3 -> 1200 | R8: =400*3 -> 1200 | S8: =400*3 -> 1200 | T8: =400*3 -> 1200 | U8: =400*3 -> 1200 | V8: =400*3 -> 1200
B9: Payroll Expenses | C9: =PayrollCost_Raw!B22*0.16 -> 9800 | D9: =PayrollCost_Raw!C22*0.16 -> 11400 | E9: =PayrollCost_Raw!D22*0.16 -> 11400 | F9: =PayrollCost_Raw!E22*0.16 -> 11400 | G9: =PayrollCost_Raw!F22*0.16 -> 11400 | H9: =PayrollCost_Raw!G22*0.16 -> 12200 | I9: =PayrollCost_Raw!H22*0.16 -> 12200 | J9: =PayrollCost_Raw!I22*0.16 -> 12200 | ... V9: =PayrollCost_Raw!U22*0.16 -> 43200
B10: Rent | C10: 0 | D10: 0 | E10: 0 | F10: 0 | G10: 0 | H10: 0 | I10: 0 | J10: 0 | K10: 0 | L10: 0 | M10: 0 | N10: 0 | O10: =20000*3 -> 60000 | P10: =20000*3 -> 60000 | Q10: =20000*3 -> 60000 | R10: =20000*3 -> 60000 | S10: =20000*3 -> 60000 | T10: =20000*3 -> 60000 | U10: =20000*3 -> 60000 | V10: =20000*3 -> 60000
B11: Research and Development | C11: =200*3 -> 600 | D11: =200*3 -> 600 | E11: =200*3 -> 600 | F11: =200*3 -> 600 | G11: =200*3 -> 600 | H11: =200*3 -> 600 | I11: =200*3 -> 600 | J11: =200*3 -> 600 | K11: =300*3 -> 900 | L11: =300*3 -> 900 | M11: =300*3 -> 900 | N11: =300*3 -> 900 | O11: =400*3 -> 1200 | P11: =400*3 -> 1200 | Q11: =400*3 -> 1200 | R11: =400*3 -> 1200 | S11: =500*3 -> 1500 | T11: =500*3 -> 1500 | U11: =500*3 -> 1500 | V11: =500*3 -> 1500
B12: Salaries and Wages | C12: =PayrollCost_Raw!B22 -> 61250 | D12: =PayrollCost_Raw!C22 -> 71250 | E12: =PayrollCost_Raw!D22 -> 71250 | F12: =PayrollCost_Raw!E22 -> 71250 | G12: =PayrollCost_Raw!F22 -> 71250 | H12: =PayrollCost_Raw!G22 -> 76250 | I12: =PayrollCost_Raw!H22 -> 76250 | J12: =PayrollCost_Raw!I22 -> 76250 | ... V12: =PayrollCost_Raw!U22 -> 270000
B13: Taxes and Licenses
B14: Telephone | C14: =100*3 -> 300 | D14: =100*3 -> 300 | E14: =100*3 -> 300 | F14: =100*3 -> 300 | G14: =100*3 -> 300 | H14: =100*3 -> 300 | I14: =100*3 -> 300 | J14: =100*3 -> 300 | ... N14: =100*3 -> 300 | O14: =300*3 -> 900 | P14: =300*3 -> 900 | Q14: =300*3 -> 900 | R14: =300*3 -> 900 | S14: =300*3 -> 900 | T14: =300*3 -> 900 | U14: =300*3 -> 900 | V14: =300*3 -> 900
B15: Travel, Utilities | C15: 250 | D15: 250 | E15: 250 | F15: 250 | G15: 250 | H15: 250 | I15: 250 | J15: 250 | K15: 250 | L15: 250 | M15: 250 | N15: 250 | O15: 250 | P15: 250 | Q15: 250 | R15: 250 | S15: 250 | T15: 250 | U15: 250 | V15: 250
B16: Web Hosting and Domains | C16: =30+100*3 -> 330 | D16: =100*3 -> 300 | E16: =100*3 -> 300 | F16: =100*3 -> 300 | G16: =100*3 -> 300 | H16: =100*3 -> 300 | I16: =100*3 -> 300 | J16: =100*3 -> 300 | K16: =100*3 -> 300 | ... V16: =100*3 -> 300
B17: Development Cost | D17: =DevCost_Raw!B3+8000 -> 26215 | G17: =DevCost_Raw!C3+8000 -> 26215 | K17: =DevCost_Raw!D3+8000 -> 44430 | O17: =DevCost_Raw!E3+8000 -> 87943 | S17: =DevCost_Raw!F3+8000 -> 110142
B18: Advertisement | F18: =DigitalMarketingCost_Raw!B2 -> 426000 | J18: =DigitalMarketingCost_Raw!C2 -> 553800 | N18: =DigitalMarketingCost_Raw!D2 -> 719940 | R18: =DigitalMarketingCost_Raw!E2 -> 935922 | V18: =DigitalMarketingCost_Raw!F2 -> 1216698.6
B19: TOTAL | C19: =SUM(C4:C18) -> 77830 | D19: =SUM(D4:D18) -> 114615 | E19: =SUM(E4:E18) -> 88400 | F19: =SUM(F4:F18) -> 514400 | G19: =SUM(G4:G18) -> 114615 | H19: =SUM(H4:H18) -> 94200 | I19: =SUM(I4:I18) -> 94200 | J19: =SUM(J4:J18) -> 648000 | ... V19: =SUM(V4:V18) -> 1598748.6

Sheet SalesForecast
C2: =HRRampUp!C2 -> Year 1 | G2: =HRRampUp!G2 -> Year 2 | K2: =HRRampUp!K2 -> Year 3 | O2: =HRRampUp!O2 -> Year 4 | S2: =HRRampUp!S2 -> Year 5
C3: =HRRampUp!C3 -> Q1 | D3: =HRRampUp!D3 -> Q2 | E3: =HRRampUp!E3 -> Q3 | F3: =HRRampUp!F3 -> Q4 | G3: =HRRampUp!G3 -> Q1 | H3: =HRRampUp!H3 -> Q2 | I3: =HRRampUp!I3 -> Q3 | J3: =HRRampUp!J3 -> Q4 | ... V3: =HRRampUp!V3 -> Q4
B4: Number of Individual User | C4: =UserBenchmarkingQuater_Raw!B3 -> 0 | D4: =UserBenchmarkingQuater_Raw!C3 -> 0 | E4: =UserBenchmarkingQuater_Raw!D3 -> 0 | F4: =UserBenchmarkingQuater_Raw!E3 -> 10000 | G4: =UserBenchmarkingQuater_Raw!F3 -> 50000 | H4: =UserBenchmarkingQuater_Raw!G3 -> 80000 | I4: =UserBenchmarkingQuater_Raw!H3 -> 100000 | J4: =UserBenchmarkingQuater_Raw!I3 -> 170000 | ... V4: =UserBenchmarkingQuater_Raw!U3 -> 2580000
B5: =B21 -> Subscription Rate (Basic) | C5: =C4*$C$21*$D$21*$E$21*$F$21 -> 0 | D5: =D4*$C$21*$D$21*$E$21*$F$21/4 -> 0 | E5: =E4*$C$21*$D$21*$E$21*$F$21/4 -> 0 | F5: =F4*$C$21*$D$21*$E$21*$F$21/4 -> 1250 | G5: =G4*$C$21*$D$21*$E$21*$F$21/4 -> 6250 | H5: =H4*$C$21*$D$21*$E$21*$F$21/4 -> 10000 | I5: =I4*$C$21*$D$21*$E$21*$F$21/4 -> 12500 | J5: =J4*$C$21*$D$21*$E$21*$F$21/4 -> 21250 | K5: =K4*$C$21*$D$21*$E$21*$F$21/4 -> 22500 | ... V5: =V4*$C$21*$D$21*$E$21*$F$21/4 -> 322500
B6: =B22 -> Subscription Rate (Deluxe) | C6: =C4*(1-$C$21)*$C$22*$D$22*$E$22*$F$22 -> 0 | D6: =D4*(1-$C$21)*$C$22*$D$22*$E$22*$F$22/4 -> 0 | E6: =E4*(1-$C$21)*$C$22*$D$22*$E$22*$F$22/4 -> 0 | F6: =F4*(1-$C$21)*$C$22*$D$22*$E$22*$F$22/4 -> 356.25 | G6: =G4*(1-$C$21)*$C$22*$D$22*$E$22*$F$22/4 -> 1781.25 | H6: =H4*(1-$C$21)*$C$22*$D$22*$E$22*$F$22/4 -> 2850 | I6: =I4*(1-$C$21)*$C$22*$D$22*$E$22*$F$22/4 -> 3562.5 | J6: =J4*(1-$C$21)*$C$22*$D$22*$E$22*$F$22/4 -> 6056.25 | K6: =K4*(1-$C$21)*$C$22*$D$22*$E$22*$F$22/4 -> 6412.5 | ... V6: =V4*(1-$C$21)*$C$22*$D$22*$E$22*$F$22/4 -> 91912.5
B7: =B23 -> Single-time Payment | C7: =C5*(1-$C$21)*$C$22*$D$22*$E$22*$F$22 -> 0 | D7: =D5*(1-$C$21)*$C$22*$D$22*$E$22*$F$22/4 -> 0 | E7: =E5*(1-$C$21)*$C$22*$D$22*$E$22*$F$22/4 -> 0 | F7: =F5*(1-$C$21)*$C$22*$D$22*$E$22*$F$22/4 -> 44.53125 | G7: =G5*(1-$C$21)*$C$22*$D$22*$E$22*$F$22/4 -> 222.65625 | H7: =H5*(1-$C$21)*$C$22*$D$22*$E$22*$F$22/4 -> 356.25 | I7: =I5*(1-$C$21)*$C$22*$D$22*$E$22*$F$22/4 -> 445.3125 | J7: =J5*(1-$C$21)*$C$22*$D$22*$E$22*$F$22/4 -> 757.03125 | K7: =K5*(1-$C$21)*$C$22*$D$22*$E$22*$F$22/4 -> 801.5625 | ... V7: =V5*(1-$C$21)*$C$22*$D$22*$E$22*$F$22/4 -> 11489.062
B8: Individual User Revenue Sum | C8: =C6*(1-$C$21)*$C$22*$D$22*$E$22*$F$22 -> 0 | D8: =SUM(D4:D7) -> 0 | E8: =SUM(E4:E7) -> 0 | F8: =SUM(F5:F7) -> 1650.7812 | G8: =SUM(G5:G7) -> 8253.9062 | H8: =SUM(H5:H7) -> 13206.25 | I8: =SUM(I5:I7) -> 16507.812 | J8: =SUM(J5:J7) -> 28063.281 | K8: =SUM(K5:K7) -> 29714.062 | L8: =SUM(L5:L7) -> 31364.844 | M8: =SUM(M5:M7) -> 41042.225 | ... V8: =SUM(V5:V7) -> 425901.56
B9: Number of Hiring Partner | C9: =UserBenchmarkingQuater_Raw!B4 -> 0 | D9: =UserBenchmarkingQuater_Raw!C4 -> 0 | E9: =UserBenchmarkingQuater_Raw!D4 -> 0 | F9: =UserBenchmarkingQuater_Raw!E4 -> 100 | G9: =UserBenchmarkingQuater_Raw!F4 -> 200 | H9: =UserBenchmarkingQuater_Raw!G4 -> 230 | I9: =UserBenchmarkingQuater_Raw!H4 -> 248.62304 | J9: =UserBenchmarkingQuater_Raw!I4 -> 700 | ... V9: =UserBenchmarkingQuater_Raw!U4 -> 3200
B10: =B24 -> Hiring Partner Subscription | C10: =C9*$C$24*$D$24*$E$24 -> 0 | D10: =D9*$C$24*$D$24*$E$24/4 -> 0 | E10: =E9*$C$24*$D$24*$E$24/4 -> 0 | F10: =F9*$C$24*$D$24*$E$24/4 -> 225 | G10: =G9*$C$24*$D$24*$E$24/4 -> 450 | H10: =H9*$C$24*$D$24*$E$24/4 -> 517.5 | I10: =I9*$C$24*$D$24*$E$24/4 -> 559.40184 | J10: =J9*$C$24*$D$24*$E$24/4 -> 1575 | K10: =K9*$C$24*$D$24*$E$24/4 -> 2025 | ... V10: =V9*$C$24*$D$24*$E$24/4 -> 7200
B11: =B26 -> Cert Course Registration (Low) | C11: =C4*$C$26*$D$26*$E$26*$F$26 -> 0 | D11: =D4*$C$26*$D$26*$E$26*$F$26/4 -> 0 | E11: =E4*$C$26*$D$26*$E$26*$F$26/4 -> 0 | F11: =F4*$C$26*$D$26*$E$26*$F$26/4 -> 93.75 | G11: =G4*$C$26*$D$26*$E$26*$F$26/4 -> 468.75 | H11: =H4*$C$26*$D$26*$E$26*$F$26/4 -> 750 | I11: =I4*$C$26*$D$26*$E$26*$F$26/4 -> 937.5 | J11: =J4*$C$26*$D$26*$E$26*$F$26/4 -> 1593.75 | K11: =K4*$C$26*$D$26*$E$26*$F$26/4 -> 1687.5 | ... V11: =V4*$C$26*$D$26*$E$26*$F$26/4 -> 24187.5
B12: =B27 -> Cert Course Registration (High) | C12: =C4*$C$27*$D$27*$E$27*$F$27 -> 0 | D12: =D4*$C$27*$D$27*$E$27*$F$27/4 -> 0 | E12: =E4*$C$27*$D$27*$E$27*$F$27/4 -> 0 | F12: =F4*$C$27*$D$27*$E$27*$F$27/4 -> 250 | G12: =G4*$C$27*$D$27*$E$27*$F$27/4 -> 1250 | H12: =H4*$C$27*$D$27*$E$27*$F$27/4 -> 2000 | I12: =I4*$C$27*$D$27*$E$27*$F$27/4 -> 2500 | J12: =J4*$C$27*$D$27*$E$27*$F$27/4 -> 4250 | K12: =K4*$C$27*$D$27*$E$27*$F$27/4 -> 4500 | ... V12: =V4*$C$27*$D$27*$E$27*$F$27/4 -> 64500
B13: =B28 -> Online Diploma Registration | C13: =C4*$C$28*$D$28*$E$28*$F$28 -> 0 | D13: =D4*$C$28*$D$28*$E$28*$F$28/4 -> 0 | E13: =E4*$C$28*$D$28*$E$28*$F$28/4 -> 0 | F13: =F4*$C$28*$D$28*$E$28*$F$28/4 -> 4687.5 | G13: =G4*$C$28*$D$28*$E$28*$F$28/4 -> 23437.5 | H13: =H4*$C$28*$D$28*$E$28*$F$28/4 -> 37500 | I13: =I4*$C$28*$D$28*$E$28*$F$28/4 -> 46875 | J13: =J4*$C$28*$D$28*$E$28*$F$28/4 -> 79687.5 | K13: =K4*$C$28*$D$28*$E$28*$F$28/4 -> 84375 | ... V13: =V4*$C$28*$D$28*$E$28*$F$28/4 -> 1209375
B14: Sum Course | C14: =SUM(C11:C13) -> 0 | D14: =SUM(D11:D13) -> 0 | E14: =SUM(E11:E13) -> 0 | F14: =SUM(F11:F13) -> 5031.25 | G14: =SUM(G11:G13) -> 25156.25 | H14: =SUM(H11:H13) -> 40250 | I14: =SUM(I11:I13) -> 50312.5 | J14: =SUM(J11:J13) -> 85531.25 | ... V14: =SUM(V11:V13) -> 1298062.5
B15: Sum Revenue | C15: 0 | D15: =D8+D10+D14 -> 0 | E15: =E8+E10+E14 -> 0 | F15: =F8+F10+F14 -> 6907.0312 | G15: =G8+G10+G14 -> 33860.156 | H15: =H8+H10+H14 -> 53973.75 | I15: =I8+I10+I14 -> 67379.714 | J15: =J8+J10+J14 -> 115169.53 | K15: =K8+K10+K14 -> 122301.56 | ... V15: =V8+V10+V14 -> 1731164.1
C20: Rate | D20: Unit Price/mo | E20: Frequency | F20: Commision
B21: Subscription Rate (Basic) | C21: 0.05 | D21: 8 | E21: =5/4 -> 1.25 | F21: 1
B22: Subscription Rate (Deluxe) | C22: 0.02 | D22: 15 | E22: 0.5 | F22: 1
B23: Single-time Payment | C23: 0.1 | D23: 1 | E23: =3/4 -> 0.75 | F23: 1
B24: Hiring Partner Subscription | C24: 0.2 | D24: 30 | E24: =6/4 -> 1.5 | F24: 1
B26: Cert Course Registration (Low) | C26: 0.1 | D26: 15 | E26: 0.25 | F26: 0.1
B27: Cert Course Registration (High) | C27: 0.02 | D27: 200 | E27: 0.25 | F27: 0.1
B28: Online Diploma Registration | C28: 0.005 | D28: 15000 | E28: 0.25 | F28: 0.1

Sheet Cashflow5yr
B2: Year | D2: Expense | E2: Revenue | F2: Profit/Loss | G2: Net Profit/Loss | H2: Outstanding Ending Balance
B3: 1 | C3: Q1 | D3: =CostExpense!C19 -> 77830 | E3: =SalesForecast!C15 -> 0 | F3: =E3-D3 -> -77830 | G3: =F3 -> -77830 | H3: =ABS(IF(G3<0,G3,D3)) -> 77830
B4: 1 | C4: Q2 | D4: =CostExpense!D19 -> 114615 | E4: =SalesForecast!D15 -> 0 | F4: =E4-D4 -> -114615 | G4: =F4+G3 -> -192445 | H4: =ABS(IF(G4<0,G4,D4)) -> 192445
B5: 1 | C5: Q3 | D5: =CostExpense!E19 -> 88400 | E5: =SalesForecast!E15 -> 0 | F5: =E5-D5 -> -88400 | G5: =F5+G4 -> -280845 | H5: =ABS(IF(G5<0,G5,D5)) -> 280845
B6: 1 | C6: Q4 | D6: =CostExpense!F19 -> 514400 | E6: =SalesForecast!F15 -> 6907.0312 | F6: =E6-D6 -> -507492.97 | G6: =F6+G5 -> -788337.97 | H6: =ABS(IF(G6<0,G6,D6)) -> 788337.97
B7: 2 | C7: Q1 | D7: =CostExpense!G19 -> 114615 | E7: =SalesForecast!G15 -> 33860.156 | F7: =E7-D7 -> -80754.844 | G7: =F7+G6 -> -869092.81 | H7: =ABS(IF(G7<0,G7,D7)) -> 869092.81
B8: 2 | C8: Q2 | D8: =CostExpense!H19 -> 94200 | E8: =SalesForecast!H15 -> 53973.75 | F8: =E8-D8 -> -40226.25 | G8: =F8+G7 -> -909319.06 | H8: =ABS(IF(G8<0,G8,D8)) -> 909319.06
B9: 2 | C9: Q3 | D9: =CostExpense!I19 -> 94200 | E9: =SalesForecast!I15 -> 67379.714 | F9: =E9-D9 -> -26820.286 | G9: =F9+G8 -> -936139.35 | H9: =ABS(IF(G9<0,G9,D9)) -> 936139.35
B10: 2 | C10: Q4 | D10: =CostExpense!J19 -> 648000 | E10: =SalesForecast!J15 -> 115169.53 | F10: =E10-D10 -> -532830.47 | G10: =F10+G9 -> -1468969.8 | H10: =ABS(IF(G10<0,G10,D10)) -> 1468969.8
B11: 3 | C11: Q1 | D11: =CostExpense!K19 -> 196930 | E11: =SalesForecast!K15 -> 122301.56 | F11: =E11-D11 -> -74628.438 | G11: =F11+G10 -> -1543598.3 | H11: =ABS(IF(G11<0,G11,D11)) -> 1543598.3
B12: 3 | C12: Q2 | D12: =CostExpense!L19 -> 152500 | E12: =SalesForecast!L15 -> 129658.59 | F12: =E12-D12 -> -22841.406 | G12: =F12+G11 -> -1566439.7 | H12: =ABS(IF(G12<0,G12,D12)) -> 1566439.7
B13: 3 | C13: Q3 | D13: =CostExpense!M19 -> 152500 | E13: =SalesForecast!M15 -> 169294.74 | F13: =E13-D13 -> 16794.741 | G13: =F13+G12 -> -1549644.9 | H13: =ABS(IF(G13<0,G13,D13)) -> 1549644.9
B14: 3 | C14: Q4 | D14: =CostExpense!N19 -> 881140 | E14: =SalesForecast!N15 -> 404971.88 | F14: =E14-D14 -> -476168.12 | G14: =F14+G13 -> -2025813 | H14: =ABS(IF(G14<0,G14,D14)) -> 2025813
B15: 4 | C15: Q1 | D15: =CostExpense!O19 -> 428093 | E15: =SalesForecast!O15 -> 605657.81 | F15: =E15-D15 -> 177564.81 | G15: =F15+G14 -> -1848248.2 | H15: =ABS(IF(G15<0,G15,D15)) -> 1848248.2
B16: 4 | C16: Q2 | D16: =CostExpense!P19 -> 357550 | E16: =SalesForecast!P15 -> 806343.75 | F16: =E16-D16 -> 448793.75 | G16: =F16+G15 -> -1399454.5 | H16: =ABS(IF(G16<0,G16,D16)) -> 1399454.5
B17: 4 | C17: Q3 | D17: =CostExpense!Q19 -> 357550 | E17: =SalesForecast!Q15 -> 944594.11 | F17: =E17-D17 -> 587044.11 | G17: =F17+G16 -> -812410.37 | H17: =ABS(IF(G17<0,G17,D17)) -> 812410.37
B18: 4 | C18: Q4 | D18: =CostExpense!R19 -> 1294472 | E18: =SalesForecast!R15 -> 1141570.3 | F18: =E18-D18 -> -152901.69 | G18: =F18+G17 -> -965312.06 | H18: =ABS(IF(G18<0,G18,D18)) -> 965312.06
B19: 5 | C19: Q1 | D19: =CostExpense!S19 -> 492192 | E19: =SalesForecast!S15 -> 1275435.9 | F19: =E19-D19 -> 783243.94 | G19: =F19+G18 -> -182068.12 | H19: =ABS(IF(G19<0,G19,D19)) -> 182068.12
B20: 5 | C20: Q2 | D20: =CostExpense!T19 -> 382050 | E20: =SalesForecast!T15 -> 1342706.2 | F20: =E20-D20 -> 960656.25 | G20: =F20+G19 -> 778588.13 | H20: =ABS(IF(G20<0,G20,D20)) -> 382050
B21: 5 | C21: Q3 | D21: =CostExpense!U19 -> 382050 | E21: =SalesForecast!U15 -> 1472636.4 | F21: =E21-D21 -> 1090586.4 | G21: =F21+G20 -> 1869174.5 | H21: =ABS(IF(G21<0,G21,D21)) -> 382050
B22: 5 | C22: Q4 | D22: =CostExpense!V19 -> 1598748.6 | E22: =SalesForecast!V15 -> 1731164.1 | F22: =E22-D22 -> 132415.46 | G22: =F22+G21 -> 2001590 | H22: =ABS(IF(G22<0,G22,D22)) -> 1598748.6

Sheet UserBenchmarking_Raw
A1: Year | B1: 1 | C1: 2 | D1: 3 | E1: 4 | F1: 5 | G1: 6 | H1: 7 | I1: 8 | J1: 9 | K1: 10
A2: Linkedin | C2: 1000000 | D2: 4000000 | E2: 42000000 | F2: 78000000 | G2: 116000000 | H2: 174000000 | I2: 238000000 | J2: 313000000 | K2: 380000000
A3: Glassdoor | C3: 1200000 | D3: =2000000 -> 2000000 | E3: =2*1000000*12 -> 24000000 | F3: =3.5*1000000*12 -> 42000000 | G3: =F3+((H3-F3)/(H1-F1)) -> 45000000 | H3: =4*1000000*12 -> 48000000 | I3: =5*1000000*12 -> 60000000 | J3: =6*1000000*12 -> 72000000 | K3: =10*1000000*12 -> 120000000
A4: Coursera | C4: =1*1000000 -> 1000000 | D4: =4*1000000 -> 4000000 | E4: =6*1000000 -> 6000000 | F4: =11*1000000 -> 11000000 | G4: =18*1000000 -> 18000000 | H4: =37.3*1000000 -> 37300000 | I4: =46.4*1000000 -> 46400000 | J4: =76.6*1000000 -> 76600000 | K4: =92*1000000 -> 92000000
A5: Boss Zhipin | C5: =D5/((E5-D5)/D5) -> 5716302 | D5: =9*1000000 -> 9000000 | E5: =23.17*1000000 -> 23170000 | F5: =E5+(H5-E5)/(H1-E1) -> 27446667 | G5: =F5+(H5-F5)/(H1-F1) -> 31723333 | H5: =3*1000000*12 -> 36000000 | I5: =40*1000000*12 -> 480000000 | J5: =50*1000000*12 -> 600000000 | K5: =46.6*1000000*12 -> 559200000
A6: Bubroo | B6: 0 | C6: 100000 | D6: =C6+C6*C13 -> 248623.04 | E6: =D6+D6*D13 -> 1406244 | F6: =E6+E6*E13 -> 2194434.3 | G6: =F6+F6*F13 -> 2803800.3 | H6: =G6+G6*G13 -> 3878850.8 | I6: =H6+H6*H13 -> 11187710 | J6: =I6+I6*I13 -> 14515848 | K6: =J6+J6*J13 -> 18021611
A7: BB Hiring Partner | B7: 0 | C7: 100 | D7: =C7+C7*C13 -> 248.62304 | E7: =D7+D7*D13 -> 1406.244 | F7: =E7+E7*E13 -> 2194.4343 | G7: =F7+F7*F13 -> 2803.8003 | H7: =G7+G7*G13 -> 3878.8508 | I7: =H7+H7*H13 -> 11187.71 | J7: =I7+I7*I13 -> 14515.848 | K7: =J7+J7*J13 -> 18021.611
K8: avg | L8: std | M8: v | N8: 1/v | O8: Raw Weight | P8: Correction | Q8: Weight
A9: Linkedin | C9: =(D2-C2)/C2 -> 3 | D9: =(E2-D2)/D2 -> 9.5 | E9: =(F2-E2)/E2 -> 0.85714286 | F9: =(G2-F2)/F2 -> 0.48717949 | G9: =(H2-G2)/G2 -> 0.5 | H9: =(I2-H2)/H2 -> 0.36781609 | I9: =(J2-I2)/I2 -> 0.31512605 | J9: =(K2-J2)/J2 -> 0.21405751 | K9: =AVERAGE(C9:J9) -> 1.9051652 | L9: =_xlfn.STDEV.P(C9:J9) -> 2.9940611 | M9: =POWER(L9,2) -> 8.9644018 | N9: =1/M9 -> 0.11155234 | O9: =N9/$N$13 -> 0.066782556 | P9: 0.1 | Q9: =O9+P9 -> 0.16678256
A10: Glassdoor | C10: =(D3-C3)/C3 -> 0.66666667 | D10: =(E3-D3)/D3 -> 11 | E10: =(F3-E3)/E3 -> 0.75 | F10: =(G3-F3)/F3 -> 0.071428571 | G10: =(H3-G3)/G3 -> 0.066666667 | H10: =(I3-H3)/H3 -> 0.25 | I10: =(J3-I3)/I3 -> 0.2 | J10: =(K3-J3)/J3 -> 0.66666667 | K10: =AVERAGE(C10:J10) -> 1.7089286 | L10: =_xlfn.STDEV.P(C10:J10) -> 3.5213623 | M10: =POWER(L10,2) -> 12.399993 | N10: =1/M10 -> 0.08064521 | O10: =N10/$N$13 -> 0.048279518 | P10: 0.2 | Q10: =O10+P10 -> 0.24827952
A11: Coursera | C11: =(D4-C4)/C4 -> 3 | D11: =(E4-D4)/D4 -> 0.5 | E11: =(F4-E4)/E4 -> 0.83333333 | F11: =(G4-F4)/F4 -> 0.63636364 | G11: =(H4-G4)/G4 -> 1.0722222 | H11: =(I4-H4)/H4 -> 0.24396783 | I11: =(J4-I4)/I4 -> 0.65086207 | J11: =(K4-J4)/J4 -> 0.20104439 | K11: =AVERAGE(C11:J11) -> 0.89222418 | L11: =_xlfn.STDEV.P(C11:J11) -> 0.84069259 | M11: =POWER(L11,2) -> 0.70676403 | N11: =1/M11 -> 1.4148994 | O11: =N11/$N$13 -> 0.84705169 | P11: =SUM(P9,P10,P12)-1 -> -0.6 | Q11: =O11+P11 -> 0.24705169
A12: Boss Zhipin | C12: =(D5-C5)/C5 -> 0.57444444 | D12: =(E5-D5)/D5 -> 1.5744444 | E12: =(F5-E5)/E5 -> 0.18457776 | F12: =(G5-F5)/F5 -> 0.15581734 | G12: =(H5-G5)/G5 -> 0.13481139 | H12: =(I5-H5)/H5 -> 12.333333 | I12: =(J5-I5)/I5 -> 0.25 | J12: =(K5-J5)/J5 -> -0.068 | K12: =AVERAGE(C12:J12) -> 1.8924286 | L12: =_xlfn.STDEV.P(C12:J12) -> 3.975131 | M12: =POWER(L12,2) -> 15.801666 | N12: =1/M12 -> 0.063284465 | O12: =N12/$N$13 -> 0.037886236 | P12: 0.1 | Q12: =O12+P12 -> 0.13788624
A13: W AVG | C13: =C9*$Q$9+C10*$Q$10+C11*$Q$11+C12*$Q$12 -> 1.4862304 | D13: =D9*$Q$9+D10*$Q$10+D11*$Q$11+D12*$Q$12 -> 4.656129 | E13: =E9*$Q$9+E10*$Q$10+E11*$Q$11+E12*$Q$12 -> 0.56049326 | F13: =F9*$Q$9+F10*$Q$10+F11*$Q$11+F12*$Q$12 -> 0.27768707 | G13: =G9*$Q$9+G10*$Q$10+G11*$Q$11+G12*$Q$12 -> 0.38342619 | H13: =H9*$Q$9+H10*$Q$10+H11*$Q$11+H12*$Q$12 -> 1.8842848 | I13: =I9*$Q$9+I10*$Q$10+I11*$Q$11+I12*$Q$12 -> 0.29748156 | J13: =J9*$Q$9+J10*$Q$10+J11*$Q$11+J12*$Q$12 -> 0.24151283 | N13: =SUM(N9:N12) -> 1.6703814
K15: Forecast
K16: RAW

Sheet UserBenchmarkingQuater_Raw
B1: =HRRampUp!C2 -> Year 1 | F1: =HRRampUp!G2 -> Year 2 | J1: =HRRampUp!K2 -> Year 3 | N1: =HRRampUp!O2 -> Year 4 | R1: =HRRampUp!S2 -> Year 5
B2: =HRRampUp!C3 -> Q1 | C2: =HRRampUp!D3 -> Q2 | D2: =HRRampUp!E3 -> Q3 | E2: =HRRampUp!F3 -> Q4 | F2: =HRRampUp!G3 -> Q1 | G2: =HRRampUp!H3 -> Q2 | H2: =HRRampUp!I3 -> Q3 | I2: =HRRampUp!J3 -> Q4 | ... U2: =HRRampUp!V3 -> Q4
A3: Individual User | B3: =UserBenchmarking_Raw!$B$6 -> 0 | C3: =UserBenchmarking_Raw!$B$6 -> 0 | D3: =UserBenchmarking_Raw!$B$6 -> 0 | E3: 10000 | F3: 50000 | G3: 80000 | H3: =UserBenchmarking_Raw!C6 -> 100000 | I3: 170000 | J3: 180000 | K3: 190000 | L3: =UserBenchmarking_Raw!D6 -> 248623.04 | M3: 600000 | N3: 900000 | O3: 1200000 | P3: =UserBenchmarking_Raw!E6 -> 1406244 | Q3: 1700000 | R3: 1900000 | S3: 2000000 | T3: =UserBenchmarking_Raw!F6 -> 2194434.3 | U3: 2580000
A4: Hiring Partner | B4: =UserBenchmarking_Raw!$B$7 -> 0 | C4: =UserBenchmarking_Raw!$B$7 -> 0 | D4: =UserBenchmarking_Raw!$B$7 -> 0 | E4: =UserBenchmarking_Raw!C7 -> 100 | F4: 200 | G4: 230 | H4: =UserBenchmarking_Raw!D7 -> 248.62304 | I4: 700 | J4: 900 | K4: 1200 | L4: =UserBenchmarking_Raw!E7 -> 1406.244 | M4: 1800 | N4: 1900 | O4: 2000 | P4: =UserBenchmarking_Raw!F7 -> 2194.4343 | Q4: 2500 | R4: 2600 | S4: 2800 | T4: =UserBenchmarking_Raw!G7 -> 2803.8003 | U4: 3200

Sheet DigitalMarketingCost_Raw
A1: Years | B1: 1 | C1: 2 | D1: 3 | E1: 4 | F1: 5 | G1: 6 | H1: 7 | I1: 8 | J1: 9
B2: =$Q$3*$Q$4*$T$3+$R$5*$R$6*$T$5+$R$7*$R$8*$T$5+$S$9*$T$9 -> 426000 | C2: =B2*(1+B6) -> 553800 | D2: =C2*(1+C6) -> 719940 | E2: =D2*(1+D6) -> 935922 | F2: =E2*(1+E6) -> 1216698.6 | G2: =F2*(1+F6) -> 1460038.3 | H2: =G2*(1+G6) -> 1752046 | I2: =H2*(1+H6) -> 2102455.2 | J2: =I2*(1+I6) -> 2312700.7 | Q2: Ins | R2: TT | S2: Youtube | T2: Months
P3: Per click unit Price | Q3: 2 | T3: 12
P4: Click Frequency | Q4: 10000
A5: Years | B5: Marketing Investment Index | P5: Influcer unit price(low) | R5: 500 | T5: 12
B6: 0.3 | C6: 0.3 | D6: 0.3 | E6: 0.3 | F6: 0.2 | G6: 0.2 | H6: 0.2 | I6: 0.1 | P6: Frequency(Low) | R6: 5
P7: Influcer unit price(High) | R7: 1000
P8: Frequency(High) | R8: 3
P9: Monthly Lump-sum | S9: 10000 | T9: 12

Sheet DevCost_Raw
B1: 1 | C1: 2 | D1: 3 | E1: 4 | F1: 5 | G1: 6 | H1: 7
B2: =UserBenchmarking_Raw!C6 -> 100000 | C2: =UserBenchmarking_Raw!C6 -> 100000 | D2: =UserBenchmarking_Raw!D6 -> 248623.04 | E2: =UserBenchmarking_Raw!E6 -> 1406244 | F2: =UserBenchmarking_Raw!F6 -> 2194434.3 | G2: =UserBenchmarking_Raw!G6 -> 2803800.3 | H2: =UserBenchmarking_Raw!H6 -> 3878850.8
A3: Cloud Cost | B3: 18215 | C3: 18215 | D3: 36430 | E3: 79943 | F3: 102142 | G3: 141306 | H3: 407568

Sheet PayrollCost_Raw
B1: =HRRampUp!C2 -> Year 1 | F1: =HRRampUp!G2 -> Year 2 | J1: =HRRampUp!K2 -> Year 3 | N1: =HRRampUp!O2 -> Year 4 | R1: =HRRampUp!S2 -> Year 5
B2: =HRRampUp!C3 -> Q1 | C2: =HRRampUp!D3 -> Q2 | D2: =HRRampUp!E3 -> Q3 | E2: =HRRampUp!F3 -> Q4 | F2: =HRRampUp!G3 -> Q1 | G2: =HRRampUp!H3 -> Q2 | H2: =HRRampUp!I3 -> Q3 | I2: =HRRampUp!J3 -> Q4 | ... U2: =HRRampUp!V3 -> Q4
A3: =HRRampUp!B4 -> CTO | B3: =IF(HRRampUp!C4*PayrollBreakdown_Raw!$D$3=0,"",HRRampUp!C4*PayrollBreakdown_Raw!$D$3) -> 37500 | C3: =IF(HRRampUp!D4*PayrollBreakdown_Raw!$D$3=0,"",HRRampUp!D4*PayrollBreakdown_Raw!$D$3) -> 37500 | D3: =IF(HRRampUp!E4*PayrollBreakdown_Raw!$D$3=0,"",HRRampUp!E4*PayrollBreakdown_Raw!$D$3) -> 37500 | E3: =IF(HRRampUp!F4*PayrollBreakdown_Raw!$D$3=0,"",HRRampUp!F4*PayrollBreakdown_Raw!$D$3) -> 37500 | F3: =IF(HRRampUp!G4*PayrollBreakdown_Raw!$D$3=0,"",HRRampUp!G4*PayrollBreakdown_Raw!$D$3) -> 37500 | G3: =IF(HRRampUp!H4*PayrollBreakdown_Raw!$D$3=0,"",HRRampUp!H4*PayrollBreakdown_Raw!$D$3) -> 37500 | H3: =IF(HRRampUp!I4*PayrollBreakdown_Raw!$D$3=0,"",HRRampUp!I4*PayrollBreakdown_Raw!$D$3) -> 37500 | I3: =IF(HRRampUp!J4*PayrollBreakdown_Raw!$D$3=0,"",HRRampUp!J4*PayrollBreakdown_Raw!$D$3) -> 37500 | ... U3: =IF(HRRampUp!V4*PayrollBreakdown_Raw!$D$3=0,"",HRRampUp!V4*PayrollBreakdown_Raw!$D$3) -> 37500
A4: =HRRampUp!B5 -> Full-Stack Developer | B4: =IF(HRRampUp!C5*PayrollBreakdown_Raw!$D$4=0,"",HRRampUp!C5*PayrollBreakdown_Raw!$D$4) | C4: =IF(HRRampUp!D5*PayrollBreakdown_Raw!$D$4=0,"",HRRampUp!D5*PayrollBreakdown_Raw!$D$4) | D4: =IF(HRRampUp!E5*PayrollBreakdown_Raw!$D$4=0,"",HRRampUp!E5*PayrollBreakdown_Raw!$D$4) | E4: =IF(HRRampUp!F5*PayrollBreakdown_Raw!$D$4=0,"",HRRampUp!F5*PayrollBreakdown_Raw!$D$4) | F4: =IF(HRRampUp!G5*PayrollBreakdown_Raw!$D$4=0,"",HRRampUp!G5*PayrollBreakdown_Raw!$D$4) | G4: =IF(HRRampUp!H5*PayrollBreakdown_Raw!$D$4=0,"",HRRampUp!H5*PayrollBreakdown_Raw!$D$4) | H4: =IF(HRRampUp!I5*PayrollBreakdown_Raw!$D$4=0,"",HRRampUp!I5*PayrollBreakdown_Raw!$D$4) | I4: =IF(HRRampUp!J5*PayrollBreakdown_Raw!$D$4=0,"",HRRampUp!J5*PayrollBreakdown_Raw!$D$4) | ... U4: =IF(HRRampUp!V5*PayrollBreakdown_Raw!$D$4=0,"",HRRampUp!V5*PayrollBreakdown_Raw!$D$4) -> 10000
A5: =HRRampUp!B6 -> UI/UX Designer | B5: =IF(HRRampUp!C6*PayrollBreakdown_Raw!$D$5=0,"",HRRampUp!C6*PayrollBreakdown_Raw!$D$5) -> 3750 | C5: =IF(HRRampUp!D6*PayrollBreakdown_Raw!$D$5=0,"",HRRampUp!D6*PayrollBreakdown_Raw!$D$5) -> 3750 | D5: =IF(HRRampUp!E6*PayrollBreakdown_Raw!$D$5=0,"",HRRampUp!E6*PayrollBreakdown_Raw!$D$5) -> 3750 | E5: =IF(HRRampUp!F6*PayrollBreakdown_Raw!$D$5=0,"",HRRampUp!F6*PayrollBreakdown_Raw!$D$5) -> 3750 | F5: =IF(HRRampUp!G6*PayrollBreakdown_Raw!$D$5=0,"",HRRampUp!G6*PayrollBreakdown_Raw!$D$5) -> 3750 | G5: =IF(HRRampUp!H6*PayrollBreakdown_Raw!$D$5=0,"",HRRampUp!H6*PayrollBreakdown_Raw!$D$5) -> 3750 | H5: =IF(HRRampUp!I6*PayrollBreakdown_Raw!$D$5=0,"",HRRampUp!I6*PayrollBreakdown_Raw!$D$5) -> 3750 | I5: =IF(HRRampUp!J6*PayrollBreakdown_Raw!$D$5=0,"",HRRampUp!J6*PayrollBreakdown_Raw!$D$5) -> 3750 | ... U5: =IF(HRRampUp!V6*PayrollBreakdown_Raw!$D$5=0,"",HRRampUp!V6*PayrollBreakdown_Raw!$D$5) -> 3750
A6: =HRRampUp!B7 -> Solution Architect | B6: =IF(HRRampUp!C7*PayrollBreakdown_Raw!$D$6=0,"",HRRampUp!C7*PayrollBreakdown_Raw!$D$6) -> 10000 | C6: =IF(HRRampUp!D7*PayrollBreakdown_Raw!$D$6=0,"",HRRampUp!D7*PayrollBreakdown_Raw!$D$6) -> 10000 | D6: =IF(HRRampUp!E7*PayrollBreakdown_Raw!$D$6=0,"",HRRampUp!E7*PayrollBreakdown_Raw!$D$6) -> 10000 | E6: =IF(HRRampUp!F7*PayrollBreakdown_Raw!$D$6=0,"",HRRampUp!F7*PayrollBreakdown_Raw!$D$6) -> 10000 | F6: =IF(HRRampUp!G7*PayrollBreakdown_Raw!$D$6=0,"",HRRampUp!G7*PayrollBreakdown_Raw!$D$6) -> 10000 | G6: =IF(HRRampUp!H7*PayrollBreakdown_Raw!$D$6=0,"",HRRampUp!H7*PayrollBreakdown_Raw!$D$6) -> 10000 | H6: =IF(HRRampUp!I7*PayrollBreakdown_Raw!$D$6=0,"",HRRampUp!I7*PayrollBreakdown_Raw!$D$6) -> 10000 | I6: =IF(HRRampUp!J7*PayrollBreakdown_Raw!$D$6=0,"",HRRampUp!J7*PayrollBreakdown_Raw!$D$6) -> 10000 | ... U6: =IF(HRRampUp!V7*PayrollBreakdown_Raw!$D$6=0,"",HRRampUp!V7*PayrollBreakdown_Raw!$D$6) -> 10000
A7: =HRRampUp!B8 -> Backend Engineer | B7: =IF(HRRampUp!C8*PayrollBreakdown_Raw!$D$7=0,"",HRRampUp!C8*PayrollBreakdown_Raw!$D$7) | C7: =IF(HRRampUp!D8*PayrollBreakdown_Raw!$D$7=0,"",HRRampUp!D8*PayrollBreakdown_Raw!$D$7) | D7: =IF(HRRampUp!E8*PayrollBreakdown_Raw!$D$7=0,"",HRRampUp!E8*PayrollBreakdown_Raw!$D$7) | E7: =IF(HRRampUp!F8*PayrollBreakdown_Raw!$D$7=0,"",HRRampUp!F8*PayrollBreakdown_Raw!$D$7) | F7: =IF(HRRampUp!G8*PayrollBreakdown_Raw!$D$7=0,"",HRRampUp!G8*PayrollBreakdown_Raw!$D$7) | G7: =IF(HRRampUp!H8*PayrollBreakdown_Raw!$D$7=0,"",HRRampUp!H8*PayrollBreakdown_Raw!$D$7) | H7: =IF(HRRampUp!I8*PayrollBreakdown_Raw!$D$7=0,"",HRRampUp!I8*PayrollBreakdown_Raw!$D$7) | I7: =IF(HRRampUp!J8*PayrollBreakdown_Raw!$D$7=0,"",HRRampUp!J8*PayrollBreakdown_Raw!$D$7) | ... U7: =IF(HRRampUp!V8*PayrollBreakdown_Raw!$D$7=0,"",HRRampUp!V8*PayrollBreakdown_Raw!$D$7) -> 8750
A8: =HRRampUp!B9 -> Data/AI Engineer | B8: =IF(HRRampUp!C9*PayrollBreakdown_Raw!$D$8=0,"",HRRampUp!C9*PayrollBreakdown_Raw!$D$8) -> 10000 | C8: =IF(HRRampUp!D9*PayrollBreakdown_Raw!$D$8=0,"",HRRampUp!D9*PayrollBreakdown_Raw!$D$8) -> 10000 | D8: =IF(HRRampUp!E9*PayrollBreakdown_Raw!$D$8=0,"",HRRampUp!E9*PayrollBreakdown_Raw!$D$8) -> 10000 | E8: =IF(HRRampUp!F9*PayrollBreakdown_Raw!$D$8=0,"",HRRampUp!F9*PayrollBreakdown_Raw!$D$8) -> 10000 | F8: =IF(HRRampUp!G9*PayrollBreakdown_Raw!$D$8=0,"",HRRampUp!G9*PayrollBreakdown_Raw!$D$8) -> 10000 | G8: =IF(HRRampUp!H9*PayrollBreakdown_Raw!$D$8=0,"",HRRampUp!H9*PayrollBreakdown_Raw!$D$8) -> 10000 | H8: =IF(HRRampUp!I9*PayrollBreakdown_Raw!$D$8=0,"",HRRampUp!I9*PayrollBreakdown_Raw!$D$8) -> 10000 | I8: =IF(HRRampUp!J9*PayrollBreakdown_Raw!$D$8=0,"",HRRampUp!J9*PayrollBreakdown_Raw!$D$8) -> 10000 | ... U8: =IF(HRRampUp!V9*PayrollBreakdown_Raw!$D$8=0,"",HRRampUp!V9*PayrollBreakdown_Raw!$D$8) -> 10000
A9: =HRRampUp!B10 -> Marketing Manager | B9: =IF(HRRampUp!C10*PayrollBreakdown_Raw!$D$15=0,"",HRRampUp!C10*PayrollBreakdown_Raw!$D$15) | C9: =IF(HRRampUp!D10*PayrollBreakdown_Raw!$D$15=0,"",HRRampUp!D10*PayrollBreakdown_Raw!$D$15) | D9: =IF(HRRampUp!E10*PayrollBreakdown_Raw!$D$15=0,"",HRRampUp!E10*PayrollBreakdown_Raw!$D$15) | E9: =IF(HRRampUp!F10*PayrollBreakdown_Raw!$D$15=0,"",HRRampUp!F10*PayrollBreakdown_Raw!$D$15) | F9: =IF(HRRampUp!G10*PayrollBreakdown_Raw!$D$15=0,"",HRRampUp!G10*PayrollBreakdown_Raw!$D$15) | G9: =IF(HRRampUp!H10*PayrollBreakdown_Raw!$D$15=0,"",HRRampUp!H10*PayrollBreakdown_Raw!$D$15) | H9: =IF(HRRampUp!I10*PayrollBreakdown_Raw!$D$15=0,"",HRRampUp!I10*PayrollBreakdown_Raw!$D$15) | I9: =IF(HRRampUp!J10*PayrollBreakdown_Raw!$D$15=0,"",HRRampUp!J10*PayrollBreakdown_Raw!$D$15) | ... U9: =IF(HRRampUp!V10*PayrollBreakdown_Raw!$D$15=0,"",HRRampUp!V10*PayrollBreakdown_Raw!$D$15) -> 22500
A10: =HRRampUp!B11 -> Digital Marketing Specialist | B10: =IF(HRRampUp!C11*PayrollBreakdown_Raw!$D$9=0,"",HRRampUp!C11*PayrollBreakdown_Raw!$D$9) | C10: =HRRampUp!D11*PayrollBreakdown_Raw!$D$9 -> 10000 | D10: =HRRampUp!E11*PayrollBreakdown_Raw!$D$9 -> 10000 | E10: =HRRampUp!F11*PayrollBreakdown_Raw!$D$9 -> 10000 | F10: =HRRampUp!G11*PayrollBreakdown_Raw!$D$9 -> 10000 | G10: =HRRampUp!H11*PayrollBreakdown_Raw!$D$9 -> 10000 | H10: =HRRampUp!I11*PayrollBreakdown_Raw!$D$9 -> 10000 | I10: =HRRampUp!J11*PayrollBreakdown_Raw!$D$9 -> 10000 | J10: =HRRampUp!K11*PayrollBreakdown_Raw!$D$9 -> 10000 | ... U10: =HRRampUp!V11*PayrollBreakdown_Raw!$D$9 -> 20000
A11: =HRRampUp!B12 -> Campus Partnerships Specialist | B11: =IF(HRRampUp!C12*PayrollBreakdown_Raw!$D$10=0,"",HRRampUp!C12*PayrollBreakdown_Raw!$D$10) | C11: =IF(HRRampUp!D12*PayrollBreakdown_Raw!$D$10=0,"",HRRampUp!D12*PayrollBreakdown_Raw!$D$10) | D11: =IF(HRRampUp!E12*PayrollBreakdown_Raw!$D$10=0,"",HRRampUp!E12*PayrollBreakdown_Raw!$D$10) | E11: =IF(HRRampUp!F12*PayrollBreakdown_Raw!$D$10=0,"",HRRampUp!F12*PayrollBreakdown_Raw!$D$10) | F11: =IF(HRRampUp!G12*PayrollBreakdown_Raw!$D$10=0,"",HRRampUp!G12*PayrollBreakdown_Raw!$D$10) | G11: =IF(HRRampUp!H12*PayrollBreakdown_Raw!$D$10=0,"",HRRampUp!H12*PayrollBreakdown_Raw!$D$10) -> 5000 | H11: =IF(HRRampUp!I12*PayrollBreakdown_Raw!$D$10=0,"",HRRampUp!I12*PayrollBreakdown_Raw!$D$10) -> 5000 | I11: =IF(HRRampUp!J12*PayrollBreakdown_Raw!$D$10=0,"",HRRampUp!J12*PayrollBreakdown_Raw!$D$10) -> 5000 | ... U11: =IF(HRRampUp!V12*PayrollBreakdown_Raw!$D$10=0,"",HRRampUp!V12*PayrollBreakdown_Raw!$D$10) -> 10000
A12: =HRRampUp!B13 -> Quality Assurance (QA) Engineer | B12: =IF(HRRampUp!C13*PayrollBreakdown_Raw!$C$16=0,"",HRRampUp!C13*PayrollBreakdown_Raw!$C$16) | C12: =IF(HRRampUp!D13*PayrollBreakdown_Raw!$C$16=0,"",HRRampUp!D13*PayrollBreakdown_Raw!$C$16) | D12: =IF(HRRampUp!E13*PayrollBreakdown_Raw!$C$16=0,"",HRRampUp!E13*PayrollBreakdown_Raw!$C$16) | E12: =IF(HRRampUp!F13*PayrollBreakdown_Raw!$C$16=0,"",HRRampUp!F13*PayrollBreakdown_Raw!$C$16) | F12: =IF(HRRampUp!G13*PayrollBreakdown_Raw!$C$16=0,"",HRRampUp!G13*PayrollBreakdown_Raw!$C$16) | G12: =IF(HRRampUp!H13*PayrollBreakdown_Raw!$C$16=0,"",HRRampUp!H13*PayrollBreakdown_Raw!$C$16) | H12: =IF(HRRampUp!I13*PayrollBreakdown_Raw!$C$16=0,"",HRRampUp!I13*PayrollBreakdown_Raw!$C$16) | I12: =IF(HRRampUp!J13*PayrollBreakdown_Raw!$C$16=0,"",HRRampUp!J13*PayrollBreakdown_Raw!$C$16) | ... U12: =IF(HRRampUp!V13*PayrollBreakdown_Raw!$C$16=0,"",HRRampUp!V13*PayrollBreakdown_Raw!$C$16) -> 30000
A13: =HRRampUp!B14 -> Customer Support Lead | B13: =IF(HRRampUp!C14*PayrollBreakdown_Raw!$D$11=0,"",HRRampUp!C14*PayrollBreakdown_Raw!$D$11) | C13: =IF(HRRampUp!D14*PayrollBreakdown_Raw!$D$11=0,"",HRRampUp!D14*PayrollBreakdown_Raw!$D$11) | D13: =IF(HRRampUp!E14*PayrollBreakdown_Raw!$D$11=0,"",HRRampUp!E14*PayrollBreakdown_Raw!$D$11) | E13: =IF(HRRampUp!F14*PayrollBreakdown_Raw!$D$11=0,"",HRRampUp!F14*PayrollBreakdown_Raw!$D$11) | F13: =IF(HRRampUp!G14*PayrollBreakdown_Raw!$D$11=0,"",HRRampUp!G14*PayrollBreakdown_Raw!$D$11) | G13: =IF(HRRampUp!H14*PayrollBreakdown_Raw!$D$11=0,"",HRRampUp!H14*PayrollBreakdown_Raw!$D$11) | H13: =IF(HRRampUp!I14*PayrollBreakdown_Raw!$D$11=0,"",HRRampUp!I14*PayrollBreakdown_Raw!$D$11) | I13: =IF(HRRampUp!J14*PayrollBreakdown_Raw!$D$11=0,"",HRRampUp!J14*PayrollBreakdown_Raw!$D$11) | ... U13: =IF(HRRampUp!V14*PayrollBreakdown_Raw!$D$11=0,"",HRRampUp!V14*PayrollBreakdown_Raw!$D$11) -> 12500
A14: =HRRampUp!B15 -> Human Resources (HR) Manager | B14: =IF(HRRampUp!C15*PayrollBreakdown_Raw!$D$13=0,"",HRRampUp!C15*PayrollBreakdown_Raw!$D$13) | C14: =IF(HRRampUp!D15*PayrollBreakdown_Raw!$D$13=0,"",HRRampUp!D15*PayrollBreakdown_Raw!$D$13) | D14: =IF(HRRampUp!E15*PayrollBreakdown_Raw!$D$13=0,"",HRRampUp!E15*PayrollBreakdown_Raw!$D$13) | E14: =IF(HRRampUp!F15*PayrollBreakdown_Raw!$D$13=0,"",HRRampUp!F15*PayrollBreakdown_Raw!$D$13) | F14: =IF(HRRampUp!G15*PayrollBreakdown_Raw!$D$13=0,"",HRRampUp!G15*PayrollBreakdown_Raw!$D$13) | G14: =IF(HRRampUp!H15*PayrollBreakdown_Raw!$D$13=0,"",HRRampUp!H15*PayrollBreakdown_Raw!$D$13) | H14: =IF(HRRampUp!I15*PayrollBreakdown_Raw!$D$13=0,"",HRRampUp!I15*PayrollBreakdown_Raw!$D$13) | I14: =IF(HRRampUp!J15*PayrollBreakdown_Raw!$D$13=0,"",HRRampUp!J15*PayrollBreakdown_Raw!$D$13) | ... U14: =IF(HRRampUp!V15*PayrollBreakdown_Raw!$D$13=0,"",HRRampUp!V15*PayrollBreakdown_Raw!$D$13) -> 7500
A15: =HRRampUp!B16 -> Product Manager | B15: =IF(HRRampUp!C16*PayrollBreakdown_Raw!$D$12=0,"",HRRampUp!C16*PayrollBreakdown_Raw!$D$12) | C15: =IF(HRRampUp!D16*PayrollBreakdown_Raw!$D$12=0,"",HRRampUp!D16*PayrollBreakdown_Raw!$D$12) | D15: =IF(HRRampUp!E16*PayrollBreakdown_Raw!$D$12=0,"",HRRampUp!E16*PayrollBreakdown_Raw!$D$12) | E15: =IF(HRRampUp!F16*PayrollBreakdown_Raw!$D$12=0,"",HRRampUp!F16*PayrollBreakdown_Raw!$D$12) | F15: =IF(HRRampUp!G16*PayrollBreakdown_Raw!$D$12=0,"",HRRampUp!G16*PayrollBreakdown_Raw!$D$12) | G15: =IF(HRRampUp!H16*PayrollBreakdown_Raw!$D$12=0,"",HRRampUp!H16*PayrollBreakdown_Raw!$D$12) | H15: =IF(HRRampUp!I16*PayrollBreakdown_Raw!$D$12=0,"",HRRampUp!I16*PayrollBreakdown_Raw!$D$12) | I15: =IF(HRRampUp!J16*PayrollBreakdown_Raw!$D$12=0,"",HRRampUp!J16*PayrollBreakdown_Raw!$D$12) | ... U15: =IF(HRRampUp!V16*PayrollBreakdown_Raw!$D$12=0,"",HRRampUp!V16*PayrollBreakdown_Raw!$D$12) -> 7500
A16: =HRRampUp!B17 -> DevOps Engineer | B16: =IF(HRRampUp!C17*PayrollBreakdown_Raw!$D$17=0,"",HRRampUp!C17*PayrollBreakdown_Raw!$D$17) | C16: =IF(HRRampUp!D17*PayrollBreakdown_Raw!$D$17=0,"",HRRampUp!D17*PayrollBreakdown_Raw!$D$17) | D16: =IF(HRRampUp!E17*PayrollBreakdown_Raw!$D$17=0,"",HRRampUp!E17*PayrollBreakdown_Raw!$D$17) | E16: =IF(HRRampUp!F17*PayrollBreakdown_Raw!$D$17=0,"",HRRampUp!F17*PayrollBreakdown_Raw!$D$17) | F16: =IF(HRRampUp!G17*PayrollBreakdown_Raw!$D$17=0,"",HRRampUp!G17*PayrollBreakdown_Raw!$D$17) | G16: =IF(HRRampUp!H17*PayrollBreakdown_Raw!$D$17=0,"",HRRampUp!H17*PayrollBreakdown_Raw!$D$17) | H16: =IF(HRRampUp!I17*PayrollBreakdown_Raw!$D$17=0,"",HRRampUp!I17*PayrollBreakdown_Raw!$D$17) | I16: =IF(HRRampUp!J17*PayrollBreakdown_Raw!$D$17=0,"",HRRampUp!J17*PayrollBreakdown_Raw!$D$17) | ... U16: =IF(HRRampUp!V17*PayrollBreakdown_Raw!$D$17=0,"",HRRampUp!V17*PayrollBreakdown_Raw!$D$17) -> 30000
A17: =HRRampUp!B18 -> Customer Support Representative | B17: =IF(HRRampUp!C18*PayrollBreakdown_Raw!$D$18=0,"",HRRampUp!C18*PayrollBreakdown_Raw!$D$18) | C17: =IF(HRRampUp!D18*PayrollBreakdown_Raw!$D$18=0,"",HRRampUp!D18*PayrollBreakdown_Raw!$D$18) | D17: =IF(HRRampUp!E18*PayrollBreakdown_Raw!$D$18=0,"",HRRampUp!E18*PayrollBreakdown_Raw!$D$18) | E17: =IF(HRRampUp!F18*PayrollBreakdown_Raw!$D$18=0,"",HRRampUp!F18*PayrollBreakdown_Raw!$D$18) | F17: =IF(HRRampUp!G18*PayrollBreakdown_Raw!$D$18=0,"",HRRampUp!G18*PayrollBreakdown_Raw!$D$18) | G17: =IF(HRRampUp!H18*PayrollBreakdown_Raw!$D$18=0,"",HRRampUp!H18*PayrollBreakdown_Raw!$D$18) | H17: =IF(HRRampUp!I18*PayrollBreakdown_Raw!$D$18=0,"",HRRampUp!I18*PayrollBreakdown_Raw!$D$18) | I17: =IF(HRRampUp!J18*PayrollBreakdown_Raw!$D$18=0,"",HRRampUp!J18*PayrollBreakdown_Raw!$D$18) | ... U17: =IF(HRRampUp!V18*PayrollBreakdown_Raw!$D$18=0,"",HRRampUp!V18*PayrollBreakdown_Raw!$D$18) -> 10000
A18: =HRRampUp!B19 -> Account Manager | B18: =IF(HRRampUp!C19*PayrollBreakdown_Raw!$D$19=0,"",HRRampUp!C19*PayrollBreakdown_Raw!$D$19) | C18: =IF(HRRampUp!D19*PayrollBreakdown_Raw!$D$19=0,"",HRRampUp!D19*PayrollBreakdown_Raw!$D$19) | D18: =IF(HRRampUp!E19*PayrollBreakdown_Raw!$D$19=0,"",HRRampUp!E19*PayrollBreakdown_Raw!$D$19) | E18: =IF(HRRampUp!F19*PayrollBreakdown_Raw!$D$19=0,"",HRRampUp!F19*PayrollBreakdown_Raw!$D$19) | F18: =IF(HRRampUp!G19*PayrollBreakdown_Raw!$D$19=0,"",HRRampUp!G19*PayrollBreakdown_Raw!$D$19) | G18: =IF(HRRampUp!H19*PayrollBreakdown_Raw!$D$19=0,"",HRRampUp!H19*PayrollBreakdown_Raw!$D$19) | H18: =IF(HRRampUp!I19*PayrollBreakdown_Raw!$D$19=0,"",HRRampUp!I19*PayrollBreakdown_Raw!$D$19) | I18: =IF(HRRampUp!J19*PayrollBreakdown_Raw!$D$19=0,"",HRRampUp!J19*PayrollBreakdown_Raw!$D$19) | ... U18: =IF(HRRampUp!V19*PayrollBreakdown_Raw!$D$19=0,"",HRRampUp!V19*PayrollBreakdown_Raw!$D$19) -> 20000
A19: =HRRampUp!B20 -> Legal Counsel
A20: =HRRampUp!B21 -> Bookkeeper | B20: =IF(HRRampUp!C21*PayrollBreakdown_Raw!$D$14=0,"",HRRampUp!C21*PayrollBreakdown_Raw!$D$14) | C20: =IF(HRRampUp!D21*PayrollBreakdown_Raw!$D$14=0,"",HRRampUp!D21*PayrollBreakdown_Raw!$D$14) | D20: =IF(HRRampUp!E21*PayrollBreakdown_Raw!$D$14=0,"",HRRampUp!E21*PayrollBreakdown_Raw!$D$14) | E20: =IF(HRRampUp!F21*PayrollBreakdown_Raw!$D$14=0,"",HRRampUp!F21*PayrollBreakdown_Raw!$D$14) | F20: =IF(HRRampUp!G21*PayrollBreakdown_Raw!$D$14=0,"",HRRampUp!G21*PayrollBreakdown_Raw!$D$14) | G20: =IF(HRRampUp!H21*PayrollBreakdown_Raw!$D$14=0,"",HRRampUp!H21*PayrollBreakdown_Raw!$D$14) | H20: =IF(HRRampUp!I21*PayrollBreakdown_Raw!$D$14=0,"",HRRampUp!I21*PayrollBreakdown_Raw!$D$14) | I20: =IF(HRRampUp!J21*PayrollBreakdown_Raw!$D$14=0,"",HRRampUp!J21*PayrollBreakdown_Raw!$D$14) | ... U20: =IF(HRRampUp!V21*PayrollBreakdown_Raw!$D$14=0,"",HRRampUp!V21*PayrollBreakdown_Raw!$D$14) -> 20000
A21: =HRRampUp!B22 -> Accountant
B22: =SUM(B3:B21) -> 61250 | C22: =SUM(C3:C21) -> 71250 | D22: =SUM(D3:D21) -> 71250 | E22: =SUM(E3:E21) -> 71250 | F22: =SUM(F3:F21) -> 71250 | G22: =SUM(G3:G21) -> 76250 | H22: =SUM(H3:H21) -> 76250 | I22: =SUM(I3:I21) -> 76250 | ... U22: =SUM(U3:U21) -> 270000
B26: Year 1 | C26: =SUM(B3:E21) -> 275000
B27: Year 2 | C27: =SUM(F3:I21) -> 300000
B28: Year 3 | C28: =SUM(J3:M21) -> 512500
B29: Year 4 | C29: =SUM(N3:Q21) -> 985000
B30: Year 5 | C30: =SUM(R3:U21) -> 1080000

Sheet PayrollBreakdown_Raw
B2: Role | C2: Annual Salary (USD) | D2: Quaterly Salary (USD)
B3: CTO | C3: 150000 | D3: =C3/4 -> 37500
B4: Full-Stack Developer (Outsourced) | C4: 40000 | D4: =C4/4 -> 10000
B5: UI/UX Designer (Outsourced) | C5: 15000 | D5: =C5/4 -> 3750
B6: Solution Architect (Outsourced) | C6: 40000 | D6: =C6/4 -> 10000
B7: Backend Engineer (Outsourced) | C7: 35000 | D7: =C7/4 -> 8750
B8: Data/AI Engineer (Outsourced) | C8: 40000 | D8: =C8/4 -> 10000
B9: Digital Marketing Specialist | C9: 40000 | D9: =C9/4 -> 10000
B10: Campus Partnerships Specialist | C10: 20000 | D10: =C10/4 -> 5000
B11: Customer Support Lead | C11: 50000 | D11: =C11/4 -> 12500
B12: Product Manager (Freelance) | C12: 30000 | D12: =C12/4 -> 7500
B13: HR Manager (Freelance) | C13: 30000 | D13: =C13/4 -> 7500
B14: Bookkeeper/Accountant (Freelance) | C14: 80000 | D14: =C14/4 -> 20000
... B20: Legal Counsel (Outsourced) | C20: 15000 | D20: =C20/4 -> 3750
